hardxor/__init__.py
hardxor/__main__.py
hardxor-0.0.2.dist-info/LICENSE
hardxor-0.0.2.dist-info/METADATA
hardxor-0.0.2.dist-info/WHEEL
hardxor-0.0.2.dist-info/entry_points.txt
hardxor-0.0.2.dist-info/top_level.txt
hardxor-0.0.2.dist-info/RECORD
