Metadata-Version: 2.1
Name: hardxor
Version: 0.0.2
Summary: Xor any file byte by byte
Home-page: https://github.com/0xflotus/hardxor
Author: 0xflotus
Author-email: 0xflotus+pypi@gmail.com
License: MIT
Platform: UNKNOWN
Classifier: Development Status :: 4 - Beta
Classifier: Intended Audience :: Developers
Classifier: License :: OSI Approved :: MIT License
Classifier: Programming Language :: Python :: 3
Classifier: Programming Language :: Python :: 3.9
License-File: LICENSE
Requires-Dist: argparse
